adaswarm/__init__.py
adaswarm/data.py
adaswarm/model.py
adaswarm/nn/__init__.py
adaswarm/particle.py
adaswarm/rempso.py
adaswarm/resnet.py
adaswarm/utils/__init__.py
adaswarm/utils/matrix.py
adaswarm/utils/options.py
adaswarm/utils/progressbar.py
adaswarm-0.0.2.dist-info/LICENSE
adaswarm-0.0.2.dist-info/WHEEL
adaswarm-0.0.2.dist-info/METADATA
adaswarm-0.0.2.dist-info/RECORD
