Metadata-Version: 2.1
Name: adaswarm
Version: 0.0.2
Summary: An implementation of particle swarm optimisation loss function for PyTorch
Home-page: https://github.com/AdaSwarm/AdaSwarm
License: MIT
Keywords: PyTorch,PSO,swarm,Adam,Optimizer,Cross Entropy,Computer vision
Author: Frank Kelly
Maintainer: Frank Kelly
Requires-Python: >=3.9.0,<3.11
Classifier: License :: OSI Approved :: MIT License
Classifier: Programming Language :: Python :: 3
Classifier: Programming Language :: Python :: 3.9
Requires-Dist: matplotlib (>=3.5.1,<4.0.0)
Requires-Dist: pandas (>=1.4.0,<2.0.0)
Requires-Dist: scikit-learn (>=1.0.2,<2.0.0)
Requires-Dist: scipy (>=1.7.0,<2.0.0)
Requires-Dist: seaborn (>=0.11.2,<0.12.0)
Requires-Dist: tabulate (>=0.8.9,<0.9.0)
Requires-Dist: torch (>=1.10.0,<2.0.0)
Requires-Dist: torchvision (>=0.11.1,<0.12.0)
Requires-Dist: visidata (>=2.8,<3.0)
Project-URL: Repository, https://github.com/AdaSwarm/AdaSwarm
Project-URL: issues, https://github.com/AdaSwarm/AdaSwarm/issues
